itly_plugin_mixpanel/__init__.py
itly_plugin_mixpanel/_mixpanel_plugin.py
itly_plugin_mixpanel-0.1.10.dist-info/WHEEL
itly_plugin_mixpanel-0.1.10.dist-info/METADATA
itly_plugin_mixpanel-0.1.10.dist-info/RECORD
