Metadata-Version: 2.1
Name: itly-plugin-mixpanel
Version: 0.1.10
Summary: Iteratively Analytics SDK - Mixpanel Plugin
License: MIT
Author: Iteratively
Requires-Python: >=3.6,<4.0
Classifier: License :: OSI Approved :: MIT License
Classifier: Programming Language :: Python :: 3
Classifier: Programming Language :: Python :: 3.6
Classifier: Programming Language :: Python :: 3.7
Classifier: Programming Language :: Python :: 3.8
Classifier: Programming Language :: Python :: 3.9
Requires-Dist: mixpanel (>=4.7.0,<5.0.0)
